{
"companyName": "Funambiguation",
"productName": "Flappy Eagle",
"productVersion": "0.2",
"dataUrl": "FlappyEagle.data.unityweb",
"wasmCodeUrl": "FlappyEagle.wasm.code.unityweb",
"wasmFrameworkUrl": "FlappyEagle.wasm.framework.unityweb",
"graphicsAPI": ["WebGL 2.0","WebGL 1.0"],
"webglContextAttributes": {"preserveDrawingBuffer": false},
"splashScreenStyle": "Dark",
"backgroundColor": "#231F20",
"cacheControl": {"default": "must-revalidate"},
"developmentBuild": false,
"multithreading": false,
"unityVersion": "2019.2.0f1"
}